ncdmv_reservation/cli.py
ncdmv_reservation/utils.py
ncdmv_reservation-0.1.8.dist-info/METADATA
ncdmv_reservation-0.1.8.dist-info/WHEEL
ncdmv_reservation-0.1.8.dist-info/entry_points.txt
ncdmv_reservation-0.1.8.dist-info/RECORD
